{
  "_note": "各スキルのSKILL.md明文要求のうち機械照合可能なものだけを宣言化。ルールの出典は各スキルの該当セクション。whenはリクエストのflagsと一致した時だけ適用される条件付きルール。",
  "_date": "2026-07-05",
  "_status": "作成者の目視承認待ち（ルールがスキル本文を忠実に写しているかの確認）",
  "rules": {
    "keihi-seisan": [
      {"id": "K1", "type": "must_match", "pattern": "\\|[^|\\n]+\\|[^|\\n]+\\|[^|\\n]+\\|", "desc": "3列表（項目|判定|理由）で出力する（出典:出力形式）"},
      {"id": "K2", "type": "must_match", "pattern": "差し戻し|要承認|承認可", "desc": "総合判定を明記する（出典:出力形式）"},
      {"id": "K3", "type": "must_not_match", "pattern": "借方|貸方", "desc": "仕訳形式への変換をしない（出典:してはいけないこと）"},
      {"id": "K4", "type": "must_match", "pattern": "要承認", "when": "上限超過あり", "desc": "上限超過は自動却下でなく要承認フラグ（出典:上限超過時の処理）"}
    ],
    "shiwake-henkan": [
      {"id": "S1", "type": "must_match", "pattern": "日付.?借方科目.?借方金額.?貸方科目.?貸方金額.?摘要|^[^,\\n]+,[^,\\n]+,[^,\\n]+,[^,\\n]+,[^,\\n]+,[^,\\n]+$", "flags": "M", "unless": "未承認データ", "desc": "CSV形式（6列）で出力する（出典:出力形式）。※拒否すべき場面には適用しない（2026-07-05較正：D05偽陽性）"},
      {"id": "S2", "type": "must_match", "pattern": "未払金（従業員立替）|未払金\\(従業員立替\\)", "when": "立替あり", "desc": "立替の貸方は未払金（従業員立替）（出典:変換規則）"},
      {"id": "S3", "type": "must_match", "pattern": "変換できません|先にkeihi-seisan|チェックしてください|変換対象外|承認されていない|承認済みデータに限り|承認後に|変換は行いません", "when": "未承認データ", "desc": "未承認データは変換せず差し戻す（出典:前提）。※2026-07-05較正：正当な拒否の言い回しを広く認識（14b偽陽性の修正）"},
      {"id": "S4", "type": "must_match", "pattern": "要確認", "when": "未知科目あり", "desc": "変換表にない科目は要確認行として出力（出典:エラー処理）"}
    ],
    "recipe-kanzan": [
      {"id": "R1", "type": "must_match", "pattern": "\\|[^|\\n]+\\|[^|\\n]+\\|", "desc": "換算前後の2列表で出力する（出典:出力）"},
      {"id": "R2", "type": "must_match", "pattern": "8〜10割|8割|様子見", "desc": "加熱時間の注意を必ず書く（出典:加熱時間の注意）"},
      {"id": "R3", "type": "must_match", "pattern": "0\\.5個|半分|半個", "when": "卵あり", "desc": "卵は0.5個単位に丸めて注記（出典:換算規則）"},
      {"id": "R4", "type": "must_match", "pattern": "9割|味", "when": "塩分調味料あり", "desc": "塩分は比例値の9割目安を提示（出典:換算規則）"}
    ],
    "gijiroku-seikei": [
      {"id": "G1", "type": "order", "patterns": ["決定事項", "アクションアイテム", "議論の要約", "保留|持ち越し", "次回"], "desc": "テンプレート順序を守る（出典:テンプレート構成・してはいけないこと）"},
      {"id": "G2", "type": "must_match", "pattern": "\\|\\s*担当\\s*\\|.*内容.*\\|.*期日.*\\|", "desc": "アクションアイテムは担当|内容|期日|依存の表（出典:アクションアイテムの形式）"},
      {"id": "G3", "type": "must_match", "pattern": "期日未定", "when": "期日不明あり", "desc": "期日不明は期日未定と明記・勝手に設定しない（出典:アクションアイテムの形式）"},
      {"id": "G4", "type": "must_match", "pattern": "（？）|\\(？\\)|\\(\\?\\)", "when": "不明固有名詞あり", "desc": "聞き取り不明の固有名詞は（？）を付ける（出典:固有名詞の扱い）"},
      {"id": "G5", "type": "must_match", "pattern": "決定事項.{0,20}\\d+.{0,10}件|件数", "desc": "末尾に件数を報告する（出典:出力後の確認）"}
    ],
    "eitango-test": [
      {"id": "E1", "type": "count_min", "pattern": "^\\s*\\d{1,2}[.．)）]", "flags": "M", "n": 20, "desc": "20問出題する（出典:形式）"},
      {"id": "E2", "type": "must_match", "pattern": "解答", "desc": "解答を別ブロックに置く（出典:解答）"}
    ],
    "travel-shiori": [
      {"id": "T1", "type": "order", "patterns": ["日程|時刻", "宿泊", "持ち物", "緊急連絡"], "desc": "日程表→宿泊→持ち物→緊急連絡先の4ブロック（出典:構成）"},
      {"id": "T2", "type": "must_match", "pattern": "未定", "when": "未確定項目あり", "desc": "未確定は未定と明記・勝手に埋めない（出典:規則）"},
      {"id": "T3", "type": "must_match", "pattern": "要確認", "desc": "移動所要時間には要確認を付ける（出典:規則）"}
    ]
  }
}
